TenorGrabber/__init__.py
TenorGrabber/tenorgrabber.py
tests/__init__.py
tests/tenorgrabber.py
TenorGrabber-1.0.5.dist-info/LICENSE
TenorGrabber-1.0.5.dist-info/METADATA
TenorGrabber-1.0.5.dist-info/WHEEL
TenorGrabber-1.0.5.dist-info/top_level.txt
TenorGrabber-1.0.5.dist-info/RECORD
