Metadata-Version: 2.1
Name: TenorGrabber
Version: 1.0.5
Summary: Get the direct link to a tenor GIF on python3!
Home-page: https://github.com/user0-07161/TenorGrabber/
Author: user0
License-File: LICENSE
Requires-Dist: requests
